activity 9/sequential1.v
module shift_register (Clk,nReset,Load,ShiftR,Sin,Din,Sout);
    input wire Clk;
    input wire nReset;
    input wire Load;
    input wire ShiftR;
    input wire Sin;
    input wire [7:0] Din;
    output wire Sout;

    reg [7:0] shift_reg;

    always @(posedge Clk ) begin
        if (~nReset)
            shift_reg <= 8'b0;
        else if (Load)
            shift_reg <= Din;
        else if (ShiftR)
            shift_reg <= {Sin, shift_reg[7:1]};
    end

    assign Sout = shift_reg[0];
endmodule


module test_shift_register;
    reg Clk;
    reg nReset;
    reg Load;
    reg ShiftR;
    reg Sin;
    reg [7:0] Din;
    wire Sout;

    // Instantiate the shift register
    shift_register u1 (
        .Clk(Clk),
        .nReset(nReset),
        .Load(Load),
        .ShiftR(ShiftR),
        .Sin(Sin),
        .Din(Din),
        .Sout(Sout)
    );

    // Clock generator
    always begin
        #5 Clk = ~Clk;
    end

    // Stimulus generator
    initial begin
	$dumpfile("seq1.vcd");
		$dumpvars;
        Clk = 0;
        nReset = 0; Load = 0; ShiftR = 0; Sin = 0; Din = 0;
        #10;
        nReset = 1;
        #10;
        Load = 1; Din = 8'b10101010;
        #10;
        Load = 0; ShiftR = 1; Sin = 1;
		#5
		Sin =0;
		#5 
		Sin = 1;
		#5
		nReset =0;
		Load=1;
		
        #50;
        $finish;
    end
endmodule

activity 9/seq1.vcd
$date
	Wed May 22 11:50:46 2024
$end
$version
	Icarus Verilog
$end
$timescale
	1s
$end
$scope module test_shift_register $end
$var wire 1 ! Sout $end
$var reg 1 " Clk $end
$var reg 8 # Din [7:0] $end
$var reg 1 $ Load $end
$var reg 1 % ShiftR $end
$var reg 1 & Sin $end
$var reg 1 ' nReset $end
$scope module u1 $end
$var wire 1 " Clk $end
$var wire 8 ( Din [7:0] $end
$var wire 1 $ Load $end
$var wire 1 % ShiftR $end
$var wire 1 & Sin $end
$var wire 1 ' nReset $end
$var wire 1 ! Sout $end
$var reg 8 ) shift_reg [7:0] $end
$upscope $end
$upscope $end
$enddefinitions $end
#0
$dumpvars
bx )
b0 (
0'
0&
0%
0$
b0 #
0"
x!
$end
#5
0!
b0 )
1"
#10
0"
1'
#15
1"
#20
0"
b10101010 #
b10101010 (
1$
#25
b10101010 )
1"
#30
0"
1&
1%
0$
#35
1!
b1010101 )
1"
0&
#40
0"
1&
#45
0!
b0 )
1"
1$
0'
