act2/fullAdder.v
module halfAdder(X, Y, S, C);
  input X, Y;
  output C, S;
  xor(S, X, Y);
  and(C, X, Y);
endmodule

module fullAdder(X, Y, Z, S, C);
  input X, Y, Z;
  output C, S;
  wire sumWire, carryWire, carryWire1;
  
  halfAdder ha0(X, Y, sumWire, carryWire);
  halfAdder ha1(sumWire, Z, S, carryWire1);
  or(C, carryWire, carryWire1);
endmodule


module fullAdder_stimulus_generator(x,y,z);
	output reg x,y,z;
	
	initial
	begin
		x=0;
		y=0;
		z=0;
		
		$dumpfile("fullAdder.vcd");
		$dumpvars;
		
		x=0; y=0; z=0;
		#2
		x=0; y=0; z=1;
		#2
		x=0; y=1; z=0;
		#2
		x=0; y=1; z=1;
		#2
		x=1; y=0; z=0;
		#2
		x=1; y=0; z=1;
		#2
		x=1; y=1; z=0;
		#2
		x=1; y=1; z=1;
		#2
		
		$finish;
	end
endmodule


module fullAdder_testbench();
	wire X,Y,Z;

	fullAdder FA(X,Y,Z,S1,C1);
	fullAdder_stimulus_generator FASG(X,Y,Z);
endmodule

act2/fullAdder.vcd
$date
	Tue Feb 20 09:39:49 2024
$end
$version
	Icarus Verilog
$end
$timescale
	1s
$end
$scope module fullAdder_testbench $end
$var wire 1 ! Z $end
$var wire 1 " Y $end
$var wire 1 # X $end
$var wire 1 $ S1 $end
$var wire 1 % C1 $end
$scope module FA $end
$var wire 1 % C $end
$var wire 1 & sumWire $end
$var wire 1 ' carryWire1 $end
$var wire 1 ( carryWire $end
$var wire 1 ! Z $end
$var wire 1 " Y $end
$var wire 1 # X $end
$var wire 1 $ S $end
$scope module ha0 $end
$var wire 1 ( C $end
$var wire 1 & S $end
$var wire 1 " Y $end
$var wire 1 # X $end
$upscope $end
$scope module ha1 $end
$var wire 1 ' C $end
$var wire 1 $ S $end
$var wire 1 & X $end
$var wire 1 ! Y $end
$upscope $end
$upscope $end
$scope module FASG $end
$var reg 1 # x $end
$var reg 1 " y $end
$var reg 1 ! z $end
$upscope $end
$upscope $end
$enddefinitions $end
#0
$dumpvars
0(
0'
0&
0%
0$
0#
0"
0!
$end
#2
1$
1!
#4
1&
0!
1"
#6
1%
1'
0$
1!
#8
0%
0'
1$
0!
0"
1#
#10
1%
1'
0$
1!
#12
0'
1(
0&
0!
1"
#14
1$
1!
