act4/parityGenEnable.v
module parityGenEnable(A,B,C,D,out);
	input A,B,C,D;
	output out;
wire term1, term2, term3, term4;

assign term1 = A & B & (~C) & (~D);
assign term2 = A & (~B) & (~C) & D;
assign term3 = A & B & C & D;
assign term4 = A & (~B) & C & (~D);

assign out = term1 | term2 | term3 | term4;
endmodule



module parity_stimulus_generator(A,B,C,D);
	output reg A,B,C,D;
		
	initial
	begin
		
		A=0;
		B=0;
		C=0;
		D=0;
		
		$dumpfile("parityGenEnable.vcd");
		$dumpvars;
		A=0; B=0; C=0;D=0;
		#2
		A=0; B=0; C=0;D=1;
		#2
		A=0; B=0; C=1;D=0;
		#2
		A=0; B=0; C=1;D=1;
		#2
		A=0; B=1; C=0;D=0;
		#2		
		A=0; B=1; C=0;D=1;
		#2		
		A=0; B=1; C=1;D=0;
		#2		
		A=0; B=1; C=1;D=1;
		#2	
		A=1; B=0; C=0;D=0;
		#2	
		A=1; B=0; C=0;D=1;
		#2	
		A=1; B=0; C=1;D=0;
		#2	
		A=1; B=0; C=1;D=1;
		#2	
		A=1; B=1; C=0;D=0;
		#2	
		A=1; B=1; C=0;D=1;
		#2			
		A=1; B=1; C=1;D=0;
		#2	
		A=1; B=1; C=1;D=1;
		#2	
		$finish;
	end
endmodule

module act3bus_testbench();
	wire A,B,C,D;
	
	parityGenEnable evenParity(A,B,C,D,out);
	parity_stimulus_generator parityGen(A,B,C,D);
endmodule

act4/act3bus.vcd
$date
	Sun Mar 10 17:31:26 2024
$end
$version
	Icarus Verilog
$end
$timescale
	1s
$end
$scope module act3bus_testbench $end
$var wire 1 ! out $end
$var wire 1 " D $end
$var wire 1 # C $end
$var wire 1 $ B $end
$var wire 1 % A $end
$scope module bus $end
$var wire 1 ! out $end
$var wire 1 " D $end
$var wire 1 # C $end
$var wire 1 $ B $end
$var wire 1 % A $end
$upscope $end
$scope module bus1 $end
$var reg 1 % A $end
$var reg 1 $ B $end
$var reg 1 # C $end
$var reg 1 " D $end
$upscope $end
$upscope $end
$enddefinitions $end
#0
$dumpvars
0%
0$
0#
0"
0!
$end
#2
1"
#4
0"
1#
#6
1"
#8
0"
0#
1$
#10
1"
#12
0"
1#
#14
1!
1"
#16
0!
0"
0#
0$
1%
#18
1"
#20
0"
1#
#22
1!
1"
#24
0!
0"
0#
1$
#26
1!
1"
#28
0"
1#
#30
1"
