act4/fullAdderAssign.v
module fullAdderAssign(A,B,C,S,Cout);
	input A,B,C;
	output Cout,S;
	wire w1,w2;

assign S=A^B^C;
assign Cout = (A & B) | (C & (A ^ B));
endmodule

module fullAdder_stimulus_generator(x,y,z);
	output reg x,y,z;
	
	initial
	begin
		x=0;
		y=0;
		z=0;
		
		$dumpfile("fullAdder.vcd");
		$dumpvars;
		
		x=0; y=0; z=0;
		#2
		x=0; y=0; z=1;
		#2
		x=0; y=1; z=0;
		#2
		x=0; y=1; z=1;
		#2
		x=1; y=0; z=0;
		#2
		x=1; y=0; z=1;
		#2
		x=1; y=1; z=0;
		#2
		x=1; y=1; z=1;
		#2
		
		$finish;
	end
endmodule


module fullAdder_testbench();
	wire X,Y,Z;

	fullAdderAssign FA(X,Y,Z,S,C);
	fullAdder_stimulus_generator FASG(X,Y,Z);
endmodule

act4/fullAdder.vcd
$date
	Sun Mar 10 17:21:02 2024
$end
$version
	Icarus Verilog
$end
$timescale
	1s
$end
$scope module fullAdder_testbench $end
$var wire 1 ! Z $end
$var wire 1 " Y $end
$var wire 1 # X $end
$var wire 1 $ S $end
$var wire 1 % C $end
$scope module FA $end
$var wire 1 % Cout $end
$var wire 1 $ S $end
$var wire 1 ! C $end
$var wire 1 " B $end
$var wire 1 # A $end
$upscope $end
$scope module FASG $end
$var reg 1 # x $end
$var reg 1 " y $end
$var reg 1 ! z $end
$upscope $end
$upscope $end
$enddefinitions $end
#0
$dumpvars
0%
0$
0#
0"
0!
$end
#2
1$
1!
#4
0!
1"
#6
1%
0$
1!
#8
0%
1$
0!
0"
1#
#10
1%
0$
1!
#12
0!
1"
#14
1$
1!
